vapi/__init__.py
vapi/exceptions.py
vapi/vapi.py
drizzutojr_vapi-0.0.8.dist-info/LICENSE.md
drizzutojr_vapi-0.0.8.dist-info/METADATA
drizzutojr_vapi-0.0.8.dist-info/WHEEL
drizzutojr_vapi-0.0.8.dist-info/top_level.txt
drizzutojr_vapi-0.0.8.dist-info/RECORD
